complexity_test/__init__.py
complexity_test/core/__init__.py
complexity_test/core/attention.py
complexity_test/core/block.py
complexity_test/core/dynamics.py
complexity_test/core/mlp.py
complexity_test/core/normalization.py
complexity_test/cuda/__init__.py
complexity_test/cuda/triton_dynamics.py
complexity_test/tests/__init__.py
complexity_test/tests/test_backward.py
complexity_test/tests/test_benchmark.py
complexity_test/tests/test_cuda.py
complexity_test/tests/test_forward.py
complexity_test/tests/test_triton.py
complexity_test-0.1.0.dist-info/METADATA
complexity_test-0.1.0.dist-info/WHEEL
complexity_test-0.1.0.dist-info/entry_points.txt
complexity_test-0.1.0.dist-info/top_level.txt
complexity_test-0.1.0.dist-info/RECORD
