Metadata-Version: 2.4
Name: complexity-test
Version: 0.1.0
Summary: Test package for Complexity Multicouche architecture (KQV + INL + MLP)
Author: Pacific Prime
Author-email: contact@pacific-prime.ai
Requires-Python: >=3.8
Requires-Dist: torch>=2.0.0
Provides-Extra: triton
Requires-Dist: triton>=2.0.0; extra == "triton"
Dynamic: author
Dynamic: author-email
Dynamic: provides-extra
Dynamic: requires-dist
Dynamic: requires-python
Dynamic: summary
